README.md
setup.cfg
setup.py
isharp/__init__.py
isharp.egg-info/PKG-INFO
isharp.egg-info/SOURCES.txt
isharp.egg-info/dependency_links.txt
isharp.egg-info/entry_points.txt
isharp.egg-info/top_level.txt
isharp/datahub/__init__.py
isharp/datahub/core.py
isharp/datahub/yaml_support.py
isharp/datahub/arctic_broker/__init__.py
isharp/datahub/arctic_broker/broker_impl/__init__.py
isharp/datahub/arctic_broker/broker_impl/arctic_data_broker.py
isharp/datahub/arctic_broker/broker_impl/arctic_storage_method.py
isharp/datahub/broker_client/__init__.py
isharp/datahub/broker_client/client.py
isharp/datahub/broker_client/client_utils.py
isharp/datahub/broker_client/remote_proxy.py
isharp/datahub/broker_impl/__init__.py
isharp/datahub/broker_service/__init__.py
isharp/datahub/broker_service/datahub_main.py
isharp/datahub/broker_service/datahub_webserver_main.py
isharp/datahub/broker_service/server.py
isharp/datahub/csv_files/__init__.py
isharp/datahub/csv_files/file_storage_method.py
isharp/datahub/csv_files/simple_file_broker.py
isharp/datahub/web/__init__.py
isharp/datahub/web/webconsole.py
isharp/datahub/web/templates/__init__.py
isharp/definitions/AlgoIndex.py
isharp/definitions/__init__.py
isharp/evalengine/__init__.py
isharp/evalengine/core.py
isharp/evalengine/remote_proxy.py
isharp/flow/__init__.py
isharp/flow/core.py
isharp/flow/luigi_remote_schedule.py
isharp/flow/luigiflow.py
isharp/flow/neo4jflow/Neo4jFlow.py
isharp/flow/neo4jflow/__init__.py
isharp/flow/neo4jflow/neo4jsetup.py
isharp/flow/neo4jflow/py2neoSetup.py
isharp/flow/neo4jflow/py2neoflow.py
test/__init__.py
test/test_combiBroker.py
test/test_main.py
test/data_broker/__init__.py
test/data_broker/test_abstract_broker.py
test/data_broker/test_file_data_broker.py
test/data_broker/test_matrixUrl.py
test/mongo/__init__.py
test/mongo/test_arctic_broker.py
test/mongo/test_arctic_storage_method.py
test/rpc/__init__.py
test/rpc/borker_server_unit.py
test/rpc/server_component_test.py
test/testutil/__init__.py
test/testutil/file_utils.py
test/testutil/log_utils.py
test/testutil/mongo_arctic_utils.py
test/testutil/mongo_temp_instance.py
test/testutil/pandas_utils.py