Metadata-Version: 1.1
Name: isharp
Version: 2.72
Summary: Algorithmic workbench
Home-page: https://github.com/jeremycward/isharp-core
Author: jeremycward
Author-email: jeremycward@yahoo.co.uk
License: UNKNOWN
Download-URL: https://github.com/jeremycward/isharp-core/tarball/1.00
Platform: UNKNOWN
